pattern_scope-0.1.0.dist-info/licenses/LICENSE
patternscope/__init__.py
patternscope/core.py
patternscope/metrics.py
patternscope/visualize.py
pattern_scope-0.1.0.dist-info/METADATA
pattern_scope-0.1.0.dist-info/WHEEL
pattern_scope-0.1.0.dist-info/top_level.txt
pattern_scope-0.1.0.dist-info/RECORD
