Metadata-Version: 2.4
Name: pattern-scope
Version: 0.1.0
Summary: Tiny CSV pattern analysis tool.
Author: RJ Sabouhi
License-Expression: MIT
Project-URL: Homepage, https://github.com/rjsabouhi/pattern-scope
Requires-Python: >=3.8
License-File: LICENSE
Requires-Dist: pandas
Requires-Dist: numpy
Requires-Dist: scipy
Requires-Dist: matplotlib
Dynamic: license-file
